Quamash-0.6.1.dist-info/LICENSE.txt
Quamash-0.6.1.dist-info/METADATA
Quamash-0.6.1.dist-info/RECORD
Quamash-0.6.1.dist-info/WHEEL
Quamash-0.6.1.dist-info/top_level.txt
quamash/__init__.py
quamash/_common.py
quamash/_unix.py
quamash/_windows.py
