Metadata-Version: 2.1
Name: Quamash
Version: 0.6.1
Summary: Implementation of the PEP 3156 Event-Loop with Qt.
Home-page: https://github.com/harvimt/quamash
Author: Mark Harviston, Arve Knudsen
Author-email: mark.harviston@gmail.com, arve.knudsen@gmail.com
License: BSD
Keywords: Qt,asyncio
Platform: UNKNOWN
Classifier: Development Status :: 3 - Alpha
Classifier: License :: OSI Approved :: BSD License
Classifier: Intended Audience :: Developers
Classifier: Operating System :: Microsoft :: Windows
Classifier: Operating System :: MacOS :: MacOS X
Classifier: Operating System :: POSIX
Classifier: Programming Language :: Python :: 3.3
Classifier: Programming Language :: Python :: 3.4
Classifier: Programming Language :: Python :: 3.5
Classifier: Programming Language :: Python :: 3 :: Only
Classifier: Environment :: X11 Applications :: Qt
Provides-Extra: test
